{
  "date": "2026-07-17",
  "book_id": 6,
  "author": "윤선도",
  "title": "어부사시사",
  "category": "고전시가",
  "subgenre": "연시조",
  "period": "조선중기",
  "source_rank": 1,
  "source_basis": "수능·모의평가·EBS 반복 출제",
  "importance": 5,
  "exam_count_sat": 1,
  "exam_count_mock": 2,
  "ebs_count": 0,
  "latest_year": "2015학년도",
  "reading_mode": "ranked",
  "one_line": "사계절 어부의 생활을 빌려 자연 속 유유자적한 삶의 흥취를 노래한 윤선도의 대표 연시조이다.",
  "summary": [
    "윤선도가 유배와 은거를 거듭한 뒤 보길도에 은둔하며 지은 40수의 연시조로, 봄·여름·가을·겨울 각 10수씩 사계절 어부의 하루를 담아낸다.",
    "화자는 실제 어부가 아닌 강호에 물러난 사대부로서, 배를 띄우고 낚시하며 자연과 하나 되는 즐거움을 노래한다.",
    "각 계절의 10수는 배를 띄우는 아침부터 돌아와 배를 매는 저녁까지 시간 순서에 따라 어부의 하루 여정을 유기적으로 구성한다.",
    "초장과 중장 사이에는 '배 떠라 배 떠라'와 같이 출항·귀항의 여음구가, 중장과 종장 사이에는 '지국총 지국총 어사와'라는 노 젓는 소리의 여음구가 규칙적으로 삽입된다.",
    "속세를 벗어난 물외한인의 자족감과 자연의 아름다움에 대한 예찬이 주된 정서이며, 유배와 정쟁의 현실을 초월하려는 태도가 드러난다.",
    "일반 시조의 3장 형식에 여음이 결합된 독특한 구조로, 국문 시가의 음악성과 회화적 이미지를 극대화한 조선 후기 연시조의 절정을 보여준다."
  ],
  "literary_significance": "『어부사시사』는 고려 이래 이어져 온 어부가 계열의 전통을 계승하면서도 이현보의 『어부가』를 발전시켜 완전히 새로운 형식을 창출한 작품이다. 40수의 대규모 연작으로 사계절과 하루의 시간 흐름을 유기적으로 결합했으며, 후렴구와 여음을 결합해 시조의 음악성을 극대화했다. 순우리말의 감각적 활용, 회화적 자연 묘사, 강호가도 계열의 주제 의식을 완성함으로써 조선 시조 문학의 정점으로 평가되며 이후 강호시가와 은일가사에 큰 영향을 끼쳤다.",
  "interpretations": [
    {
      "viewpoint": "주제론적 해석 — 강호가도의 완성",
      "explanation": "속세를 떠난 사대부가 자연 속에서 누리는 흥취와 안분지족의 정서를 노래한 강호가도의 절정으로 읽힌다. 어부라는 소재는 실제 노동이 아니라 정치적 갈등을 초월한 이상적 삶의 상징이다.",
      "original_quote": "지국총 지국총 어사와",
      "quote_source": "『어부사시사』 각 수 중장과 종장 사이 여음구"
    },
    {
      "viewpoint": "형식·구조 분석 — 연시조의 유기적 구성",
      "explanation": "봄·여름·가을·겨울 각 10수가 출항에서 귀항까지 하루의 시간 순서로 배열되어 사계절과 하루라는 이중의 시간 구조를 이룬다. 여음구의 규칙적 반복은 노 젓는 리듬과 결합해 음악적 통일성을 만든다.",
      "original_quote": "압개예 안개 것고 뒫뫼희 ᄒᆡ 비췬다",
      "quote_source": "『어부사시사』 춘사(春詞) 1수 초장"
    },
    {
      "viewpoint": "사회사적 해석 — 유배 문인의 현실 대응",
      "explanation": "당쟁으로 인한 유배와 은거의 산물로서, 정치 현실에서 밀려난 사대부가 자연을 이념화하며 자기 정체성을 재구성한 텍스트로 볼 수 있다. 어부의 여유는 현실도피이자 저항의 다른 이름이다.",
      "original_quote": "인간을 도라보니 머도록 더욱 됴타",
      "quote_source": "『어부사시사』 하사(夏詞) 2수 종장"
    }
  ],
  "keywords": [
    "강호가도",
    "연시조",
    "여음구",
    "사계절 구성",
    "물외한인"
  ],
  "discussion_question": "『어부사시사』의 어부는 실제 노동하는 어부가 아니라 사대부의 이상화된 자아이다. 이러한 '가상의 어부' 형상이 작품의 미학을 완성하는 동시에 현실 인식을 은폐하는 측면은 없는지 논의해 보자.",
  "perplexity_followup_prompt": "윤선도의 『어부사시사』와 이현보의 『어부가』, 그리고 중국 굴원의 「어부사」를 비교하면 각 작품 속 '어부' 형상은 어떻게 다르며, 그 차이는 무엇을 의미하는가?",
  "next_recommendations": [
    {
      "title": "면앙정가",
      "author": "송순",
      "reason": "자연 속에 정자를 짓고 은거하며 자연과 인간의 조화를 노래한 강호가사의 대표작이다. 어부사시사와 함께 조선 사대부의 강호가도 이념을 이해하는 데 핵심적인 텍스트이다.",
      "external": true
    },
    {
      "title": "어부가",
      "author": "이현보",
      "reason": "윤선도의 『어부사시사』가 직접 계승·발전시킨 원류 작품으로, 두 작품을 함께 읽으면 어부가 계열 시가의 변천과 연시조 형식의 진화를 체계적으로 파악할 수 있다.",
      "external": true
    },
    {
      "title": "율리유곡",
      "author": "김광욱",
      "reason": "벼슬을 버리고 율리에 은거하며 지은 17수의 연시조로, 강호에서의 소박한 삶과 자족감을 노래한다. 어부사시사와 같은 은일 지향의 정서를 다른 공간(전원)에서 구현한 작품이다.",
      "external": true
    }
  ],
  "source_note": "수능 기출 + EBS 연계 한국 고전 일일 리포트"
}